fileperms/__init__.py
fileperms-1.2.0.dist-info/LICENSE
fileperms-1.2.0.dist-info/METADATA
fileperms-1.2.0.dist-info/WHEEL
fileperms-1.2.0.dist-info/top_level.txt
fileperms-1.2.0.dist-info/zip-safe
fileperms-1.2.0.dist-info/RECORD
