Metadata-Version: 2.1
Name: fileperms
Version: 1.2.0
Summary: fileperms is small library for describing file permissions
Home-page: https://github.com/msztolcman/fileperms
Author: Marcin Sztolcman
Author-email: marcin@urzenia.net
License: MIT
Project-URL: Source, https://github.com/msztolcman/fileperms
Project-URL: Issues, https://github.com/msztolcman/fileperms/issues
Keywords: files,permissions,posix
Platform: UNKNOWN
Classifier: Development Status :: 5 - Production/Stable
Classifier: Intended Audience :: Developers
Classifier: Intended Audience :: System Administrators
Classifier: License :: OSI Approved :: MIT License
Classifier: Topic :: Utilities
Classifier: Topic :: Software Development
Classifier: Topic :: Software Development :: Libraries
Classifier: Programming Language :: Python :: 3
Classifier: Programming Language :: Python :: 3 :: Only
Classifier: Programming Language :: Python :: 3.7
Classifier: Programming Language :: Python :: 3.8
Classifier: Programming Language :: Python :: 3.9
Classifier: Programming Language :: Python :: 3.10
License-File: LICENSE
Provides-Extra: dev
Requires-Dist: pylint (>=2.13.9) ; extra == 'dev'
Requires-Dist: pytest (>=7.1.2) ; extra == 'dev'
Requires-Dist: twine (>=4.0.0) ; extra == 'dev'
Requires-Dist: wheel (>=0.37.1) ; extra == 'dev'
Requires-Dist: tox ; extra == 'dev'
Requires-Dist: tox-asdf ; extra == 'dev'
